Spruce_validation-0.1.3-py2.7-nspkg.pth
spruce/validation/_misc.py
spruce/validation/__init__.py
Spruce_validation-0.1.3.dist-info/top_level.txt
Spruce_validation-0.1.3.dist-info/RECORD
Spruce_validation-0.1.3.dist-info/pydist.json
Spruce_validation-0.1.3.dist-info/WHEEL
Spruce_validation-0.1.3.dist-info/namespace_packages.txt
Spruce_validation-0.1.3.dist-info/METADATA
Spruce_validation-0.1.3.dist-info/entry_points.txt
Spruce_validation-0.1.3.dist-info/DESCRIPTION.rst
