Metadata-Version: 2.0
Name: Spruce-validation
Version: 0.1.3
Summary: Validation
Home-page: UNKNOWN
Author: Ivan D Vasin
Author-email: nisavid@gmail.com
License: GNU LESSER GENERAL PUBLIC LICENSE
